{"last-status-check-time": 1618989356817, "counts": {"total-dois": 83, "current-dois": 0, "backfile-dois": 83}, "breakdowns": {"dois-by-issued-year": [[2012, 63], [2013, 16], [2014, 4]]}, "publisher": "Hindawi (International Scholarly Research Network)", "coverage": {"affiliations-current": 0, "similarity-checking-current": 0, "funders-backfile": 0.3132530152797699, "licenses-backfile": 1.0, "funders-current": 0, "affiliations-backfile": 1.0, "resource-links-backfile": 1.0, "orcids-backfile": 0.2530120611190796, "update-policies-current": 0, "open-references-backfile": 1.0, "orcids-current": 0, "similarity-checking-backfile": 1.0, "references-backfile": 1.0, "award-numbers-backfile": 0.1325301229953766, "update-policies-backfile": 0.0, "licenses-current": 0, "award-numbers-current": 0, "abstracts-backfile": 1.0, "resource-links-current": 0, "abstracts-current": 0, "open-references-current": 0, "references-current": 0}, "title": "ISRN Agronomy", "subjects": [], "coverage-type": {"all": {"last-status-check-time": 1618989349029, "affiliations": 0.9764705896377563, "abstracts": 0.9764705896377563, "orcids": 0.24705882370471954, "licenses": 0.9764705896377563, "references": 0.9764705896377563, "funders": 0.30588236451148987, "similarity-checking": 0.9764705896377563, "award-numbers": 0.12941177189350128, "update-policies": 0.0, "resource-links": 0.9764705896377563, "open-references": 1.0}, "backfile": {"last-status-check-time": 1618989346555, "affiliations": 1.0, "abstracts": 1.0, "orcids": 0.2530120611190796, "licenses": 1.0, "references": 1.0, "funders": 0.3132530152797699, "similarity-checking": 1.0, "award-numbers": 0.1325301229953766, "update-policies": 0.0, "resource-links": 1.0, "open-references": 1.0}, "current": {"last-status-check-time": 1618989343934, "affiliations": 0, "abstracts": 0, "orcids": 0, "licenses": 0, "references": 0, "funders": 0, "similarity-checking": 0, "award-numbers": 0, "update-policies": 0, "resource-links": 0, "open-references": 0}}, "flags": {"deposits-abstracts-current": false, "deposits-orcids-current": false, "deposits": true, "deposits-affiliations-backfile": true, "deposits-update-policies-backfile": false, "deposits-similarity-checking-backfile": true, "deposits-award-numbers-current": false, "deposits-resource-links-current": false, "deposits-articles": true, "deposits-affiliations-current": false, "deposits-funders-current": false, "deposits-references-backfile": true, "deposits-abstracts-backfile": true, "deposits-licenses-backfile": true, "deposits-award-numbers-backfile": true, "deposits-open-references-backfile": true, "deposits-open-references-current": false, "deposits-references-current": false, "deposits-resource-links-backfile": true, "deposits-orcids-backfile": true, "deposits-funders-backfile": true, "deposits-update-policies-current": false, "deposits-similarity-checking-current": false, "deposits-licenses-current": false}, "ISSN": ["2090-7664", "2090-7656"], "issn-type": [{"value": "2090-7664", "type": "electronic"}, {"value": "2090-7656", "type": "print"}]}