{"last-status-check-time": 1621162537960, "counts": {"total-dois": 1045, "current-dois": 268, "backfile-dois": 777}, "breakdowns": {"dois-by-issued-year": [[2015, 118], [2014, 115], [2020, 113], [2013, 107], [2019, 100], [2017, 96], [2016, 94], [2018, 85], [2011, 84], [2012, 78], [2021, 54], [2103, 1]]}, "publisher": "Joule Inc.", "coverage": {"affiliations-current": 0.0, "similarity-checking-current": 0.09328357875347137, "funders-backfile": 0.0, "licenses-backfile": 0.0, "funders-current": 0.0, "affiliations-backfile": 0.0, "resource-links-backfile": 0.0, "orcids-backfile": 0.0, "update-policies-current": 0.0, "open-references-backfile": 0.0, "orcids-current": 0.0, "similarity-checking-backfile": 0.9974259734153748, "references-backfile": 0.0, "award-numbers-backfile": 0.0, "update-policies-backfile": 0.0, "licenses-current": 0.0, "award-numbers-current": 0.0, "abstracts-backfile": 0.027027027681469917, "resource-links-current": 0.0, "abstracts-current": 0.14552238583564758, "open-references-current": 0.0, "references-current": 0.0}, "title": "Canadian Journal of Surgery", "subjects": [{"name": "Surgery", "ASJC": 2746}], "coverage-type": {"all": {"last-status-check-time": 1621162530644, "affiliations": 0.0, "abstracts": 0.05736137554049492, "orcids": 0.0, "licenses": 0.0, "references": 0.0, "funders": 0.0, "similarity-checking": 0.7648183703422546, "award-numbers": 0.0, "update-policies": 0.0, "resource-links": 0.0, "open-references": 0.0}, "backfile": {"last-status-check-time": 1621162528312, "affiliations": 0.0, "abstracts": 0.027027027681469917, "orcids": 0.0, "licenses": 0.0, "references": 0.0, "funders": 0.0, "similarity-checking": 0.9974259734153748, "award-numbers": 0.0, "update-policies": 0.0, "resource-links": 0.0, "open-references": 0.0}, "current": {"last-status-check-time": 1621162525953, "affiliations": 0.0, "abstracts": 0.14552238583564758, "orcids": 0.0, "licenses": 0.0, "references": 0.0, "funders": 0.0, "similarity-checking": 0.09328357875347137, "award-numbers": 0.0, "update-policies": 0.0, "resource-links": 0.0, "open-references": 0.0}}, "flags": {"deposits-abstracts-current": true, "deposits-orcids-current": false, "deposits": true, "deposits-affiliations-backfile": false, "deposits-update-policies-backfile": false, "deposits-similarity-checking-backfile": true, "deposits-award-numbers-current": false, "deposits-resource-links-current": false, "deposits-articles": true, "deposits-affiliations-current": false, "deposits-funders-current": false, "deposits-references-backfile": false, "deposits-abstracts-backfile": true, "deposits-licenses-backfile": false, "deposits-award-numbers-backfile": false, "deposits-open-references-backfile": false, "deposits-open-references-current": false, "deposits-references-current": false, "deposits-resource-links-backfile": false, "deposits-orcids-backfile": false, "deposits-funders-backfile": false, "deposits-update-policies-current": false, "deposits-similarity-checking-current": true, "deposits-licenses-current": false}, "ISSN": ["0008-428X", "0008-428X"], "issn-type": [{"value": "0008-428X", "type": "electronic"}, {"value": "0008-428X", "type": "print"}]}